CHANGES.txt
DEPENDENCES.txt
README.txt
setup.py
src/pd/__init__.py
src/pd.subversion.notify.egg-info/PKG-INFO
src/pd.subversion.notify.egg-info/SOURCES.txt
src/pd.subversion.notify.egg-info/dependency_links.txt
src/pd.subversion.notify.egg-info/entry_points.txt
src/pd.subversion.notify.egg-info/namespace_packages.txt
src/pd.subversion.notify.egg-info/not-zip-safe
src/pd.subversion.notify.egg-info/requires.txt
src/pd.subversion.notify.egg-info/top_level.txt
src/pd/subversion/__init__.py
src/pd/subversion/notify/__init__.py
src/pd/subversion/notify/pd.subversion.notify.txt
src/pd/subversion/notify/pdsubversionnotify.py
