Metadata-Version: 1.0
Name: pd.subversion.notify
Version: 0.0.1
Summary: This programm used in subversion postcommit hook to send list of modified files to xmlrpc server
Home-page: http://www.dreambot.ru/product/DreamBotOtherReleases/pd.subversion.notify
Author: Andrey Orlov
Author-email: cray@neural.ru
License: GPL v2.1
Platform: UNKNOWN
Classifier: Intended Audience :: Developers
Classifier: License :: OSI Approved :: GNU General Public License (GPL)
Classifier: Programming Language :: Python
Classifier: Operating System :: OS Independent
